ngstSpaceKit/__init__.py
ngstSpaceKit/argyris.py
ngstSpaceKit/bfs.py
ngstSpaceKit/bubbles.py
ngstSpaceKit/crouzeix.py
ngstSpaceKit/demo.py
ngstSpaceKit/diffops.py
ngstSpaceKit/hdiv.py
ngstSpaceKit/hermite.py
ngstSpaceKit/immersedfe.py
ngstSpaceKit/mesh_properties.py
ngstSpaceKit/morley.py
ngstSpaceKit/py.typed
ngstSpaceKit/stokes.py
ngstSpaceKit/trefftz_formulation.py
ngstSpaceKit/weak_h1.py
ngstspacekit-1.1.0.dist-info/METADATA
ngstspacekit-1.1.0.dist-info/WHEEL
ngstspacekit-1.1.0.dist-info/licenses/LICENSE
ngstspacekit-1.1.0.dist-info/RECORD
