Metadata-Version: 2.4
Name: ngstSpaceKit
Version: 1.1.0
Summary: ngstSpaceKit is an addon to ngsolve, that provides several new spaces / finite elements.
Project-URL: repository, https://codeberg.org/johann-cm/ngstspacekit
Project-URL: documentation, https://johann-cm.codeberg.page/ngstspacekit/docs/index.html
Author-email: Johann Carl Meyer <info@johannc.de>
License-Expression: LGPL-3.0-only
License-File: LICENSE
Requires-Python: >=3.10
Requires-Dist: mkl>=2025.1.0
Requires-Dist: ngsolve>=6.2.2506
Requires-Dist: ngstrefftz>=0.3.2506
Requires-Dist: xfem>=2.1.2506
